{"version":{"skyformer":"0.0.5"},"items":[{"id":"iron-ore","name":"Iron Ore","category":"ore","stack":"64","row":1},{"id":"bauxite-ore","name":"Bauxite Ore","category":"ore","stack":"64","row":1},{"id":"copper-ore","name":"Copper Ore","category":"ore","stack":"64","row":1},{"id":"gold-ore","name":"Gold Ore","category":"ore","stack":"64","row":1},{"id":"titanium-ore","name":"Titanium Ore","category":"ore","stack":"64","row":1},{"id":"neodymium-ore","name":"Neodymium Ore","category":"ore","stack":"64","row":1},{"id":"xenium-ore","name":"Xenium Ore","category":"ore","stack":"64","row":1},{"id":"salt","name":"Salt","category":"ore","stack":"64","row":1},{"id":"coal","name":"Coal","category":"ore","stack":"64","row":1},{"id":"silica","name":"Silica","category":"ore","stack":"64","row":1},{"id":"graphite","name":"Graphite","category":"ore","stack":"64","row":1},{"id":"sulphur","name":"Sulphur","category":"ore","stack":"64","row":1},{"id":"lithium","name":"Lithium","category":"ore","stack":"64","row":2},{"id":"cobalt","name":"Cobalt","category":"ore","stack":"64","row":2},{"id":"dimond","name":"Dimond","category":"ore","stack":"64","row":2},{"id":"debri","name":"Debri","category":"ore","stack":"64","row":2},{"id":"iron-bar","name":"Iron Bar","category":"materials","stack":"64","row":1},{"id":"aluminium-bar","name":"Aluminium Bar","category":"materials","stack":"64","row":1},{"id":"steel-bar","name":"Steel Bar","category":"materials","stack":"64","row":1},{"id":"copper-bar","name":"Copper Bar","category":"materials","stack":"64","row":1},{"id":"gold-bar","name":"Gold Bar","category":"materials","stack":"64","row":1},{"id":"titanium-bar","name":"Titanium Bar","category":"materials","stack":"64","row":1},{"id":"neodymium-bar","name":"Neodymium Bar","category":"materials","stack":"64","row":1},{"id":"xenium-bar","name":"Xenium Bar","category":"materials","stack":"64","row":1},{"id":"lithium-rod","name":"Lithium Rod","category":"materials","stack":"64","row":1},{"id":"soil","name":"Soil","category":"materials","stack":"64","row":1},{"id":"aluminium-plate","name":"Aluminium Plate","category":"materials","stack":"64","row":1},{"id":"aluminium-frame","name":"Aluminium Frame","category":"materials","stack":"64","row":1},{"id":"steel-beam","name":"Steel Beam","category":"materials","stack":"64","row":2},{"id":"copper-wire","name":"Copper Wire","category":"materials","stack":"64","row":2},{"id":"power-cell","name":"Power Cell","category":"materials","stack":"64","row":2},{"id":"rocket-power-cell","name":"Rocket Power Cell","category":"materials","stack":"64","row":2},{"id":"computer-chip-t1","name":"Computer Chip T1","category":"materials","stack":"64","row":2,"iconText":"T1"},{"id":"computer-chip-t2","name":"Computer Chip T2","category":"materials","stack":"64","row":2,"iconText":"T2"},{"id":"gas-canister","name":"Gas Canister","category":"materials","stack":"64","row":2},{"id":"network-chip","name":"Network Chip","category":"materials","stack":"64","row":2},{"id":"reinforced-plate","name":"Reinforced Plate","category":"materials","stack":"64","row":2},{"id":"heavy-reinforced-plate","name":"Heavy Reinforced Plate","category":"materials","stack":"64","row":2},{"id":"structural-composite","name":"Structural Composite","category":"materials","stack":"64","row":2},{"id":"high-tech-alloy","name":"High Tech Alloy","category":"materials","stack":"64","row":2},{"id":"cargo-drone","name":"Cargo Drone","category":"products","stack":"64","row":1},{"id":"repair-drone","name":"Repair Drone","category":"products","stack":"64","row":1},{"id":"repair-plate-t1","name":"Repair Plate T1","category":"products","stack":"64","row":1,"iconText":"T1"},{"id":"repair-plate-t2","name":"Repair Plate T2","category":"products","stack":"64","row":1,"iconText":"T2"},{"id":"repair-plate-t3","name":"Repair Plate T3","category":"products","stack":"64","row":1,"iconText":"T3"},{"id":"defense-module-t1","name":"defense Module T1","category":"products","stack":"64","row":1,"iconText":"T1"},{"id":"defense-module-t2","name":"defense Module T2","category":"products","stack":"64","row":1,"iconText":"T2"},{"id":"defense-module-t3","name":"defense Module T3","category":"products","stack":"64","row":1,"iconText":"T3"},{"id":"defense-module-t4","name":"defense Module T4","category":"products","stack":"64","row":1,"iconText":"T4"},{"id":"defense-module-t5","name":"defense Module T5","category":"products","stack":"64","row":1,"iconText":"T5"},{"id":"acid","name":"Acid","category":"products","stack":"64","row":1},{"id":"powdered-xenium","name":"Powdered Xenium","category":"products","stack":"64","row":1},{"id":"xenosulfate","name":"Xenosulfate","category":"products","stack":"64","row":2},{"id":"high-powered-mining-laser","name":"High Powered Mining Laser","category":"products","stack":"64","row":2},{"id":"radar-upgrade-module","name":"Radar Upgrade Module","category":"products","stack":"64","row":2},{"id":"radio-active-core","name":"Radio Active Core","category":"materials","stack":64,"row":3},{"id":"miner-t1","name":"miner-t1","category":"building","stack":"64","row":1,"machine":{"speed":1},"iconText":"T1"},{"id":"miner-t2","name":"miner-t2","category":"building","stack":"64","row":1,"machine":{"speed":2},"iconText":"T2"},{"id":"miner","name":"Miner","category":"building","stack":"64","row":1},{"id":"factory","name":"Factory","category":"building","stack":"64","row":1,"machine":{"speed":1}},{"id":"drone-view-constructor","name":"Drone View Constructor","category":"building","stack":"64","row":1},{"id":"drone-control-tower","name":"Drone Control Tower","category":"building","stack":"64","row":1},{"id":"logistic-storage","name":"Logistical Storage","category":"building","stack":"64","row":1},{"id":"mini-logistic-storage","name":"Mini Logistical Storage","category":"building","stack":"64","row":1},{"id":"geothermal-power-plant","name":"Geothermal Power Plant","category":"building","stack":"64","row":1},{"id":"nuclear-power-plant","name":"Nuclear Power Plant","category":"building","stack":"64","row":1},{"id":"lightning-tower","name":"Lightning Tower","category":"building","stack":"64","row":1},{"id":"storm-defense-system","name":"Storm defense System","category":"building","stack":"64","row":1},{"id":"weather-station","name":"Weather Station","category":"building","stack":"64","row":2},{"id":"network-tower","name":"Network Tower","category":"building","stack":"64","row":2},{"id":"network-receiver","name":"Network Receiver","category":"building","stack":"64","row":2},{"id":"storm-probe","name":"Storm Probe","category":"building","stack":"64","row":2},{"id":"floor","name":"Floor","category":"base-structure","stack":"64","row":1},{"id":"charging-platform","name":"Charging Platform","category":"base-structure","stack":"64","row":1},{"id":"charge-gem","name":"Charge Gem","category":"materials","stack":64,"row":3},{"id":"glass-floor","name":"Glass Floor","category":"base-structure","stack":"64","row":1},{"id":"foundation","name":"Foundation","category":"base-structure","stack":"64","row":1},{"id":"wall","name":"Wall","category":"base-structure","stack":"64","row":1},{"id":"glass-wall","name":"Glass Wall","category":"base-structure","stack":"64","row":1},{"id":"rail","name":"Rail","category":"base-structure","stack":"64","row":1},{"id":"sloped-rail","name":"Sloped Rail","category":"base-structure","stack":"64","row":1},{"id":"foundation-floor","name":"Foundation Floor","category":"base-structure","stack":"64","row":1},{"id":"slope-down","name":"Slope Down","category":"base-structure","stack":"64","row":1},{"id":"slope-up","name":"Slope Up","category":"base-structure","stack":"64","row":1},{"id":"door","name":"Door","category":"base-structure","stack":"64","row":1},{"id":"elevator","name":"Elevator","category":"base-structure","stack":"64","row":2},{"id":"elevator-shaft","name":"Elevator Shaft","category":"base-structure","stack":"64","row":2},{"id":"lamp","name":"Lamp","category":"base-structure","stack":"64","row":2},{"id":"tower-up","name":"Tower Up","category":"base-structure","stack":"64","row":2},{"id":"tower-down","name":"Tower Down","category":"base-structure","stack":"64","row":2},{"id":"factory-(base)","name":"Factory (Base)","category":"base-tech","stack":"64","row":1},{"id":"logistic-storage-(base)","name":"Logistical Storage (Base)","category":"base-tech","stack":"64","row":1},{"id":"mini-logistic-storage-(base)","name":"Mini Logistical Storage (Base)","category":"base-tech","stack":"64","row":1},{"id":"storm-probe-monitor","name":"Storm Probe Monitor","category":"base-tech","stack":"64","row":1},{"id":"construction-station","name":"Construction Station","category":"base-tech","stack":"64","row":1,"machine":{"speed":1}},{"id":"player-upgrade-station","name":"Player Upgrade Station","category":"base-tech","stack":"64","row":1},{"id":"small-storage","name":"Small Storage","category":"base-tech","stack":"64","row":1},{"id":"large-storage","name":"Large Storage","category":"base-tech","stack":"64","row":1},{"id":"healing-station","name":"Healing Station","category":"base-tech","stack":"64","row":1},{"id":"radiant-gem","name":"Radiant Gem","category":"materials","stack":64,"row":3},{"id":"shield-station","name":"Shield Station","category":"base-tech","stack":"64","row":1},{"id":"planter","name":"Planter","category":"base-tech","stack":"64","row":1},{"id":"large-planter","name":"Large Planter","category":"base-tech","stack":"64","row":1},{"id":"dna-processor","name":"DNA Processor","category":"base-tech","stack":"64","row":2},{"id":"resource-detector","name":"Resource Detector","category":"base-tech","stack":"64","row":2},{"id":"temperature-display","name":"Temperature Display","category":"base-tech","stack":"64","row":2},{"id":"storm-warning-display","name":"Storm Warning Display","category":"base-tech","stack":"64","row":2},{"id":"server-power-generator-t1","name":"Server Power Generator T1","category":"base-tech","stack":"64","row":2,"iconText":"T1"},{"id":"server-power-generator-t2","name":"Server Power Generator T2","category":"base-tech","stack":"64","row":2,"iconText":"T2"},{"id":"skybase-server-monitor","name":"Skybase Server Monitor","category":"base-tech","stack":"64","row":2},{"id":"server-t1","name":"Server T1","category":"base-tech","stack":"64","row":2,"iconText":"T1"},{"id":"server-t2","name":"Server T2","category":"base-tech","stack":"64","row":2,"iconText":"T2"},{"id":"mini-charge-pack","name":"Mini Charge Pack","category":"consumables","stack":"64","row":1},{"id":"charge-pack","name":"Charge Pack","category":"consumables","stack":"64","row":1},{"id":"radioactive-crystal-t2","name":"Radioactive Crystal T2","category":"materials","stack":64,"row":3,"iconText":"T2"},{"id":"movement-pack","name":"Movement Pack","category":"consumables","stack":"64","row":1},{"id":"radioactive-crystal-t1","name":"Radioactive Crystal T1","category":"materials","stack":64,"row":3,"iconText":"T1"},{"id":"health-pack","name":"Health Pack","category":"consumables","stack":"64","row":1},{"id":"radioactive-crystal-t3","name":"Radioactive Crystal T3","category":"materials","stack":64,"row":3,"iconText":"T3"},{"id":"terraform-engine-command-center","name":"Terraform Engine Command Center","category":"terraform","stack":"64","row":1},{"id":"rocket-launch-platform","name":"Rocket Launch Platform","category":"terraform","stack":"64","row":1},{"id":"gas-drone-launch-platform","name":"Gas Drone Launch Platform","category":"terraform","stack":"64","row":1},{"id":"gas-dispersion-drone","name":"Gas Dispersion Drone","category":"terraform","stack":"64","row":1},{"id":"rocket-t1","name":"Rocket T1","category":"terraform","stack":"64","row":1,"iconText":"T1"},{"id":"rocket-t2","name":"Rocket T2","category":"terraform","stack":"64","row":1,"iconText":"T2"},{"id":"rocket-t3","name":"Rocket T3","category":"terraform","stack":"64","row":1,"iconText":"T3"},{"id":"zipline-tower","name":"Zipline Tower","category":"transport","stack":"64","row":1},{"id":"base-zipline","name":"Base Zipline","category":"transport","stack":"64","row":1},{"id":"aircraft-port","name":"Aircraft Port","category":"transport","stack":"1","row":1,"machine":{"speed":1}},{"id":"basic-jet","name":"basic-jet","category":"aircraft","stack":"1","row":1},{"id":"repair-helicopter","name":"repair-helicopter","category":"aircraft","stack":"1","row":1},{"id":"powered-glider","name":"powered-glider","category":"aircraft","stack":"1","row":1},{"id":"advanced-jet","name":"advanced-jet","category":"aircraft","stack":64,"row":1}],"recipes":[{"id":"iron-ore","name":"Iron Ore","category":"ore","row":0,"time":0.16666666666666666,"producers":["miner-t1","miner-t2"],"in":{},"out":{"iron-ore":1}},{"id":"bauxite-ore","name":"Bauxite Ore","category":"ore","row":0,"time":0.16666666666666666,"producers":["miner-t1","miner-t2"],"in":{},"out":{"bauxite-ore":1}},{"id":"copper-ore","name":"Copper Ore","category":"ore","row":0,"time":0.16666666666666666,"producers":["miner-t1","miner-t2"],"in":{},"out":{"copper-ore":1}},{"id":"gold-ore","name":"Gold Ore","category":"ore","row":0,"time":0.16666666666666666,"producers":["miner-t1","miner-t2"],"in":{},"out":{"gold-ore":1}},{"id":"titanium-ore","name":"Titanium Ore","category":"ore","row":0,"time":0.16666666666666666,"producers":["miner-t1","miner-t2"],"in":{},"out":{"titanium-ore":1}},{"id":"neodymium-ore","name":"Neodymium Ore","category":"ore","row":0,"time":0.16666666666666666,"producers":["miner-t1","miner-t2"],"in":{},"out":{"neodymium-ore":1}},{"id":"xenium-ore","name":"Xenium Ore","category":"ore","row":0,"time":0.16666666666666666,"producers":["miner-t1","miner-t2"],"in":{},"out":{"xenium-ore":1}},{"id":"salt","name":"Salt","category":"ore","row":0,"time":0.16666666666666666,"producers":["miner-t1","miner-t2"],"in":{},"out":{"salt":1}},{"id":"coal","name":"Coal","category":"ore","row":0,"time":0.16666666666666666,"producers":["miner-t1","miner-t2"],"in":{},"out":{"coal":1}},{"id":"silica","name":"Silica","category":"ore","row":0,"time":0.16666666666666666,"producers":["miner-t1","miner-t2"],"in":{},"out":{"silica":1}},{"id":"graphite","name":"Graphite","category":"ore","row":0,"time":0.16666666666666666,"producers":["miner-t1","miner-t2"],"in":{},"out":{"graphite":1}},{"id":"sulphur","name":"Sulphur","category":"ore","row":0,"time":0.16666666666666666,"producers":["miner-t1","miner-t2"],"in":{},"out":{"sulphur":1}},{"id":"lithium","name":"Lithium","category":"ore","row":0,"time":0.16666666666666666,"producers":["miner-t1","miner-t2"],"in":{},"out":{"lithium":1}},{"id":"cobalt","name":"Cobalt","category":"ore","row":0,"time":0.16666666666666666,"producers":["miner-t1","miner-t2"],"in":{},"out":{"cobalt":1}},{"id":"dimond","name":"Dimond","category":"ore","row":0,"time":0.16666666666666666,"producers":["miner-t1","miner-t2"],"in":{},"out":{"dimond":1}},{"id":"iron-bar","name":"Iron Bar","category":"materials","row":1,"time":0.16666666666666666,"producers":["factory"],"in":{"iron-ore":2},"out":{"iron-bar":1}},{"id":"aluminium-bar","name":"Aluminium Bar","category":"materials","row":1,"time":0.16666666666666666,"producers":["factory"],"in":{"bauxite-ore":1,"salt":1},"out":{"aluminium-bar":1}},{"id":"steel-bar","name":"Steel Bar","category":"materials","row":1,"time":0.08333333333333333,"producers":["factory"],"in":{"iron-ore":1,"coal":2},"out":{"steel-bar":1}},{"id":"copper-bar","name":"Copper Bar","category":"materials","row":1,"time":0.08333333333333333,"producers":["factory"],"in":{"copper-ore":2},"out":{"copper-bar":1}},{"id":"gold-bar","name":"Gold Bar","category":"materials","row":1,"time":0.08333333333333333,"producers":["factory"],"in":{"gold-ore":2},"out":{"gold-bar":1}},{"id":"titanium-bar","name":"Titanium Bar","category":"materials","row":1,"time":0.041666666666666664,"producers":["factory"],"in":{"titanium-ore":2},"out":{"titanium-bar":1}},{"id":"neodymium-bar","name":"Neodymium Bar","category":"materials","row":2,"time":0.041666666666666664,"producers":["factory"],"in":{"neodymium-ore":4},"out":{"neodymium-bar":1}},{"id":"xenium-bar","name":"Xenium Bar","category":"materials","row":2,"time":0.08333333333333333,"producers":["factory"],"in":{"xenium-ore":4,"steel-bar":4},"out":{"xenium-bar":1}},{"id":"lithium-rod","name":"Lithium Rod","category":"materials","row":2,"time":0.016666666666666666,"producers":["factory"],"in":{"lithium":2},"out":{"lithium-rod":1}},{"id":"soil","name":"Soil","category":"materials","row":2,"time":0.16666666666666666,"producers":["factory"],"in":{"debri":10},"out":{"soil":1}},{"id":"aluminium-plate","name":"Aluminium Plate","category":"materials","row":2,"time":0.16666666666666666,"producers":["factory"],"in":{"aluminium-bar":1},"out":{"aluminium-plate":1}},{"id":"aluminium-frame","name":"Aluminium Frame","category":"materials","row":2,"time":0.08333333333333333,"producers":["factory"],"in":{"aluminium-bar":1},"out":{"aluminium-frame":1}},{"id":"steel-beam","name":"Steel Beam","category":"materials","row":3,"time":0.16666666666666666,"producers":["factory"],"in":{"steel-bar":2},"out":{"steel-beam":1}},{"id":"copper-wire","name":"Copper Wire","category":"materials","row":3,"time":0.041666666666666664,"producers":["factory"],"in":{"copper-bar":1},"out":{"copper-wire":1}},{"id":"power-cell","name":"Power Cell","category":"materials","row":3,"time":0.16666666666666666,"producers":["factory"],"in":{"aluminium-plate":4,"copper-wire":4},"out":{"power-cell":1}},{"id":"rocket-power-cell","name":"Rocket Power Cell","category":"materials","row":3,"time":0.16666666666666666,"producers":["factory"],"in":{"graphite":1,"power-cell":2},"out":{"rocket-power-cell":1}},{"id":"computer-chip-t1","name":"Computer Chip T1","category":"materials","row":3,"time":0.041666666666666664,"producers":["factory"],"in":{"silica":1,"copper-wire":4},"out":{"computer-chip-t1":1}},{"id":"computer-chip-t2","name":"Computer Chip T2","category":"materials","row":3,"time":0.020833333333333332,"producers":["factory"],"in":{"graphite":4,"copper-wire":8},"out":{"computer-chip-t2":1}},{"id":"gas-canister","name":"Gas Canister","category":"materials","row":4,"time":0.08333333333333333,"producers":["factory"],"in":{"aluminium-frame":8},"out":{"gas-canister":1}},{"id":"network-chip","name":"Network Chip","category":"materials","row":4,"time":0.16666666666666666,"producers":["factory"],"in":{"silica":2,"copper-bar":2,"gold-bar":2},"out":{"network-chip":1}},{"id":"reinforced-plate","name":"Reinforced Plate","category":"materials","row":4,"time":0.16666666666666666,"producers":["factory"],"in":{"titanium-bar":1,"aluminium-plate":1},"out":{"reinforced-plate":1}},{"id":"heavy-reinforced-plate","name":"Heavy Reinforced Plate","category":"materials","row":4,"time":0.041666666666666664,"producers":["factory"],"in":{"cobalt":1,"dimond":2,"aluminium-plate":2},"out":{"heavy-reinforced-plate":1}},{"id":"structural-composite","name":"Structural Composite","category":"materials","row":4,"time":0.16666666666666666,"producers":["factory"],"in":{"sulphur":6,"titanium-bar":4,"aluminium-frame":4},"out":{"structural-composite":1}},{"id":"high-tech-alloy","name":"High Tech Alloy","category":"materials","row":4,"time":0.16666666666666666,"producers":["factory"],"in":{"cobalt":8,"aluminium-bar":1,"neodymium-bar":1},"out":{"high-tech-alloy":1}},{"id":"cargo-drone","name":"Cargo Drone","category":"products","row":1,"time":0.16666666666666666,"producers":["factory"],"in":{"aluminium-plate":2,"computer-chip-t1":1},"out":{"cargo-drone":1}},{"id":"repair-drone","name":"Repair Drone","category":"products","row":1,"time":0.16666666666666666,"producers":["factory"],"in":{"iron-bar":2,"computer-chip-t1":1},"out":{"repair-drone":1}},{"id":"repair-plate-t1","name":"Repair Plate T1","category":"products","row":1,"time":0.16666666666666666,"producers":["factory"],"in":{"aluminium-plate":1},"out":{"repair-plate-t1":1}},{"id":"repair-plate-t2","name":"Repair Plate T2","category":"products","row":1,"time":0.16666666666666666,"producers":["factory"],"in":{"gold-bar":2,"aluminium-plate":1},"out":{"repair-plate-t2":1}},{"id":"repair-plate-t3","name":"Repair Plate T3","category":"products","row":1,"time":0.16666666666666666,"producers":["factory"],"in":{"cobalt":6,"aluminium-plate":1},"out":{"repair-plate-t3":1}},{"id":"defense-module-t1","name":"defense Module T1","category":"products","row":1,"time":0.16666666666666666,"producers":["factory"],"in":{"aluminium-plate":2,"repair-drone":1},"out":{"defense-module-t1":1}},{"id":"defense-module-t2","name":"defense Module T2","category":"products","row":2,"time":0.16666666666666666,"producers":["factory"],"in":{"gold-bar":1,"repair-drone":1},"out":{"defense-module-t2":1}},{"id":"defense-module-t3","name":"defense Module T3","category":"products","row":2,"time":0.16666666666666666,"producers":["factory"],"in":{"reinforced-plate":6,"repair-drone":1},"out":{"defense-module-t3":1}},{"id":"defense-module-t4","name":"defense Module T4","category":"products","row":2,"time":0.16666666666666666,"producers":["factory"],"in":{"heavy-reinforced-plate":6,"repair-drone":1},"out":{"defense-module-t4":1}},{"id":"defense-module-t5","name":"defense Module T5","category":"products","row":2,"time":0.020833333333333332,"producers":["factory"],"in":{"xenium-bar":2,"repair-drone":1},"out":{"defense-module-t5":1}},{"id":"acid","name":"Acid","category":"products","row":2,"time":0.16666666666666666,"producers":["factory"],"in":{"salt":8,"sulphur":8},"out":{"acid":1}},{"id":"powdered-xenium","name":"Powdered Xenium","category":"products","row":2,"time":0.16666666666666666,"producers":["factory"],"in":{"xenium-bar":1},"out":{"powdered-xenium":1}},{"id":"xenosulfate","name":"Xenosulfate","category":"products","row":3,"time":0.16666666666666666,"producers":["factory"],"in":{"sulphur":4,"powdered-xenium":1},"out":{"xenosulfate":1}},{"id":"high-powered-mining-laser","name":"High Powered Mining Laser","category":"products","row":3,"time":0.041666666666666664,"producers":["factory"],"in":{"neodymium-bar":1,"lithium-rod":1},"out":{"high-powered-mining-laser":1}},{"id":"radar-upgrade-module","name":"Radar Upgrade Module","category":"products","row":4,"time":0.16666666666666666,"producers":["factory"],"in":{"radio-active-core":8,"neodymium-bar":4},"out":{"radar-upgrade-module":1}},{"id":"miner","name":"Miner","category":"building","row":1,"time":0.16666666666666666,"producers":["construction-station"],"in":{"iron-bar":12},"out":{"miner":1}},{"id":"factory","name":"Factory","category":"building","row":1,"time":0.16666666666666666,"producers":["construction-station"],"in":{"iron-bar":10},"out":{"factory":1}},{"id":"drone-view-constructor","name":"Drone View Constructor","category":"building","row":1,"time":0.16666666666666666,"producers":["construction-station"],"in":{"iron-bar":4},"out":{"drone-view-constructor":1}},{"id":"drone-control-tower","name":"Drone Control Tower","category":"building","row":1,"time":0.16666666666666666,"producers":["construction-station"],"in":{"aluminium-frame":16},"out":{"drone-control-tower":1}},{"id":"logistic-storage","name":"Logistical Storage","category":"building","row":0,"time":0.16666666666666666,"producers":["construction-station"],"in":{"aluminium-frame":12},"out":{"logistic-storage":1}},{"id":"mini-logistic-storage","name":"Mini Logistical Storage","category":"building","row":1,"time":0.16666666666666666,"producers":["construction-station"],"in":{"aluminium-frame":8},"out":{"mini-logistic-storage":1}},{"id":"geothermal-power-plant","name":"Geothermal Power Plant","category":"building","row":1,"time":0.16666666666666666,"producers":["construction-station"],"in":{"aluminium-frame":8,"power-cell":8},"out":{"geothermal-power-plant":1}},{"id":"nuclear-power-plant","name":"Nuclear Power Plant","category":"building","row":2,"time":0.16666666666666666,"producers":["construction-station"],"in":{"steel-beam":4,"network-chip":1},"out":{"nuclear-power-plant":1}},{"id":"lightning-tower","name":"Lightning Tower","category":"building","row":2,"time":0.16666666666666666,"producers":["construction-station"],"in":{"gold-bar":48,"aluminium-frame":32,"structural-composite":4},"out":{"lightning-tower":1}},{"id":"storm-defense-system","name":"Storm defense System","category":"building","row":2,"time":0.16666666666666666,"producers":["construction-station"],"in":{"steel-beam":16,"repair-drone":8},"out":{"storm-defense-system":1}},{"id":"weather-station","name":"Weather Station","category":"building","row":2,"time":0.16666666666666666,"producers":["construction-station"],"in":{"aluminium-frame":16,"network-chip":8},"out":{"weather-station":1}},{"id":"network-tower","name":"Network Tower","category":"building","row":2,"time":0.16666666666666666,"producers":["construction-station"],"in":{"steel-beam":16,"network-chip":16},"out":{"network-tower":1}},{"id":"network-receiver","name":"Network Receiver","category":"building","row":2,"time":0.16666666666666666,"producers":["construction-station"],"in":{"steel-beam":32,"network-chip":32,"heavy-reinforced-plate":32,"high-tech-alloy":16},"out":{"network-receiver":1}},{"id":"storm-probe","name":"Storm Probe","category":"building","row":2,"time":0.16666666666666666,"producers":["construction-station"],"in":{"steel-beam":4,"network-chip":1},"out":{"storm-probe":1}},{"id":"floor","name":"Floor","category":"base-structure","row":1,"time":0.16666666666666666,"producers":["construction-station"],"in":{"iron-bar":1,"aluminium-plate":4},"out":{"floor":1}},{"id":"charging-platform","name":"Charging Platform","category":"base-structure","row":1,"time":0.16666666666666666,"producers":["construction-station"],"in":{"charge-gem":4,"iron-bar":2,"aluminium-plate":8},"out":{"charging-platform":1}},{"id":"glass-floor","name":"Glass Floor","category":"base-structure","row":1,"time":0.16666666666666666,"producers":["construction-station"],"in":{"silica":2,"iron-bar":1,"aluminium-plate":2},"out":{"glass-floor":1}},{"id":"foundation","name":"Foundation","category":"base-structure","row":1,"time":0.16666666666666666,"producers":["construction-station"],"in":{"iron-bar":2,"aluminium-plate":8},"out":{"foundation":1}},{"id":"wall","name":"Wall","category":"base-structure","row":1,"time":0.16666666666666666,"producers":["construction-station"],"in":{"iron-bar":1,"aluminium-plate":2},"out":{"wall":1}},{"id":"glass-wall","name":"Glass Wall","category":"base-structure","row":1,"time":0.16666666666666666,"producers":["construction-station"],"in":{"silica":2,"iron-bar":1,"aluminium-plate":1},"out":{"glass-wall":1}},{"id":"rail","name":"Rail","category":"base-structure","row":1,"time":0.16666666666666666,"producers":["construction-station"],"in":{"aluminium-plate":2},"out":{"rail":1}},{"id":"sloped-rail","name":"Sloped Rail","category":"base-structure","row":2,"time":0.16666666666666666,"producers":["construction-station"],"in":{"aluminium-plate":2},"out":{"sloped-rail":1}},{"id":"foundation-floor","name":"Foundation Floor","category":"base-structure","row":2,"time":0.16666666666666666,"producers":["construction-station"],"in":{"iron-bar":1,"aluminium-plate":12},"out":{"foundation-floor":1}},{"id":"slope-down","name":"Slope Down","category":"base-structure","row":2,"time":0.16666666666666666,"producers":["construction-station"],"in":{"iron-bar":1,"aluminium-plate":12},"out":{"slope-down":1}},{"id":"slope-up","name":"Slope Up","category":"base-structure","row":2,"time":0.16666666666666666,"producers":["construction-station"],"in":{"iron-bar":1,"aluminium-plate":12},"out":{"slope-up":1}},{"id":"door","name":"Door","category":"base-structure","row":2,"time":0.16666666666666666,"producers":["construction-station"],"in":{"steel-bar":8,"aluminium-plate":12},"out":{"door":1}},{"id":"elevator","name":"Elevator","category":"base-structure","row":2,"time":0.16666666666666666,"producers":["construction-station"],"in":{"steel-bar":12,"aluminium-plate":16},"out":{"elevator":1}},{"id":"elevator-shaft","name":"Elevator Shaft","category":"base-structure","row":2,"time":0.16666666666666666,"producers":["construction-station"],"in":{"steel-bar":24,"aluminium-plate":16},"out":{"elevator-shaft":1}},{"id":"lamp","name":"Lamp","category":"base-structure","row":3,"time":0.16666666666666666,"producers":["construction-station"],"in":{"steel-bar":2},"out":{"lamp":1}},{"id":"tower-up","name":"Tower Up","category":"base-structure","row":3,"time":0.16666666666666666,"producers":["construction-station"],"in":{"iron-bar":4,"gold-bar":8,"aluminium-plate":16},"out":{"tower-up":1}},{"id":"tower-down","name":"Tower Down","category":"base-structure","row":3,"time":0.16666666666666666,"producers":["construction-station"],"in":{"iron-bar":4,"gold-bar":8,"aluminium-plate":16},"out":{"tower-down":1}},{"id":"factory-(base)","name":"Factory (Base)","category":"base-tech","row":2,"time":0.16666666666666666,"producers":["construction-station"],"in":{"iron-bar":10,"aluminium-plate":4},"out":{"factory-(base)":1}},{"id":"logistic-storage-(base)","name":"Logistical Storage (Base)","category":"base-tech","row":2,"time":0.16666666666666666,"producers":["construction-station"],"in":{"aluminium-plate":4,"aluminium-frame":12},"out":{"logistic-storage-(base)":1}},{"id":"mini-logistic-storage-(base)","name":"Mini Logistical Storage (Base)","category":"base-tech","row":2,"time":0.16666666666666666,"producers":["construction-station"],"in":{"aluminium-plate":4,"aluminium-frame":8},"out":{"mini-logistic-storage-(base)":1}},{"id":"storm-probe-monitor","name":"Storm Probe Monitor","category":"base-tech","row":3,"time":0.16666666666666666,"producers":["construction-station"],"in":{"iron-bar":4,"network-chip":1},"out":{"storm-probe-monitor":1}},{"id":"construction-station","name":"Construction Station","category":"base-tech","row":1,"time":0.16666666666666666,"producers":["construction-station"],"in":{"iron-bar":4},"out":{"construction-station":1}},{"id":"player-upgrade-station","name":"Player Upgrade Station","category":"base-tech","row":1,"time":0.16666666666666666,"producers":["construction-station"],"in":{"iron-bar":4},"out":{"player-upgrade-station":1}},{"id":"small-storage","name":"Small Storage","category":"base-tech","row":1,"time":0.16666666666666666,"producers":["construction-station"],"in":{"iron-bar":8},"out":{"small-storage":1}},{"id":"large-storage","name":"Large Storage","category":"base-tech","row":1,"time":0.16666666666666666,"producers":["construction-station"],"in":{"structural-composite":2},"out":{"large-storage":1}},{"id":"healing-station","name":"Healing Station","category":"base-tech","row":1,"time":0.16666666666666666,"producers":["construction-station"],"in":{"radiant-gem":2,"iron-bar":8,"aluminium-plate":8},"out":{"healing-station":1}},{"id":"shield-station","name":"Shield Station","category":"base-tech","row":1,"time":0.16666666666666666,"producers":["construction-station"],"in":{"charge-gem":2,"iron-bar":8,"aluminium-plate":8},"out":{"shield-station":1}},{"id":"planter","name":"Planter","category":"base-tech","row":1,"time":0.16666666666666666,"producers":["construction-station"],"in":{"iron-bar":4,"soil":2},"out":{"planter":1}},{"id":"large-planter","name":"Large Planter","category":"base-tech","row":2,"time":0.16666666666666666,"producers":["construction-station"],"in":{"iron-bar":4,"soil":3},"out":{"large-planter":1}},{"id":"dna-processor","name":"DNA Processor","category":"base-tech","row":2,"time":0.16666666666666666,"producers":["construction-station"],"in":{"aluminium-frame":16,"computer-chip-t1":8},"out":{"dna-processor":1}},{"id":"resource-detector","name":"Resource Detector","category":"base-tech","row":2,"time":0.16666666666666666,"producers":["construction-station"],"in":{"aluminium-frame":4},"out":{"resource-detector":1}},{"id":"temperature-display","name":"Temperature Display","category":"base-tech","row":2,"time":0.16666666666666666,"producers":["construction-station"],"in":{"iron-bar":4,"computer-chip-t1":2},"out":{"temperature-display":1}},{"id":"storm-warning-display","name":"Storm Warning Display","category":"base-tech","row":3,"time":0.16666666666666666,"producers":["construction-station"],"in":{"iron-bar":4,"computer-chip-t1":2},"out":{"storm-warning-display":1}},{"id":"server-power-generator-t1","name":"Server Power Generator T1","category":"base-tech","row":3,"time":0.16666666666666666,"producers":["construction-station"],"in":{"lithium-rod":6,"aluminium-frame":8,"power-cell":4},"out":{"server-power-generator-t1":1}},{"id":"server-power-generator-t2","name":"Server Power Generator T2","category":"base-tech","row":3,"time":0.16666666666666666,"producers":["construction-station"],"in":{"steel-bar":16,"power-cell":4,"high-tech-alloy":4},"out":{"server-power-generator-t2":1}},{"id":"skybase-server-monitor","name":"Skybase Server Monitor","category":"base-tech","row":3,"time":0.16666666666666666,"producers":["construction-station"],"in":{"iron-bar":8,"computer-chip-t1":2,"network-chip":2},"out":{"skybase-server-monitor":1}},{"id":"server-t1","name":"Server T1","category":"base-tech","row":3,"time":0.16666666666666666,"producers":["construction-station"],"in":{"computer-chip-t1":8,"network-chip":8},"out":{"server-t1":1}},{"id":"server-t2","name":"Server T2","category":"base-tech","row":3,"time":0.16666666666666666,"producers":["construction-station"],"in":{"computer-chip-t2":8,"network-chip":16,"structural-composite":1,"high-tech-alloy":4},"out":{"server-t2":1}},{"id":"mini-charge-pack","name":"Mini Charge Pack","category":"consumables","row":1,"time":0.16666666666666666,"producers":["construction-station"],"in":{"charge-gem":1},"out":{"mini-charge-pack":1}},{"id":"charge-pack","name":"Charge Pack","category":"consumables","row":1,"time":0.16666666666666666,"producers":["construction-station"],"in":{"radioactive-crystal-t2":2},"out":{"charge-pack":1}},{"id":"movement-pack","name":"Movement Pack","category":"consumables","row":1,"time":0.16666666666666666,"producers":["construction-station"],"in":{"radioactive-crystal-t1":2},"out":{"movement-pack":1}},{"id":"health-pack","name":"Health Pack","category":"consumables","row":1,"time":0.16666666666666666,"producers":["construction-station"],"in":{"radioactive-crystal-t3":2},"out":{"health-pack":1}},{"id":"terraform-engine-command-center","name":"Terraform Engine Command Center","category":"terraform","row":1,"time":0.16666666666666666,"producers":["construction-station"],"in":{"iron-bar":16,"computer-chip-t1":8},"out":{"terraform-engine-command-center":1}},{"id":"rocket-launch-platform","name":"Rocket Launch Platform","category":"terraform","row":1,"time":0.16666666666666666,"producers":["construction-station"],"in":{"steel-beam":48,"computer-chip-t1":16},"out":{"rocket-launch-platform":1}},{"id":"gas-drone-launch-platform","name":"Gas Drone Launch Platform","category":"terraform","row":1,"time":0.16666666666666666,"producers":["construction-station"],"in":{"aluminium-frame":128,"computer-chip-t2":8},"out":{"gas-drone-launch-platform":1}},{"id":"gas-dispersion-drone","name":"Gas Dispersion Drone","category":"terraform","row":1,"time":0.16666666666666666,"producers":["construction-station","factory"],"in":{"rocket-power-cell":1,"computer-chip-t2":2,"gas-canister":1},"out":{"gas-dispersion-drone":1}},{"id":"rocket-t1","name":"Rocket T1","category":"terraform","row":1,"time":0.16666666666666666,"producers":["construction-station","factory"],"in":{"radioactive-crystal-t1":1,"aluminium-plate":16,"rocket-power-cell":1,"gas-canister":1},"out":{"rocket-t1":1}},{"id":"rocket-t2","name":"Rocket T2","category":"terraform","row":1,"time":0.16666666666666666,"producers":["construction-station","factory"],"in":{"radioactive-crystal-t2":1,"rocket-power-cell":6,"gas-canister":1,"reinforced-plate":20},"out":{"rocket-t2":1}},{"id":"rocket-t3","name":"Rocket T3","category":"terraform","row":1,"time":0.16666666666666666,"producers":["construction-station","factory"],"in":{"radioactive-crystal-t3":1,"rocket-power-cell":18,"gas-canister":1,"heavy-reinforced-plate":24},"out":{"rocket-t3":1}},{"id":"zipline-tower","name":"Zipline Tower","category":"transport","row":1,"time":0.16666666666666666,"producers":["construction-station"],"in":{"aluminium-frame":12},"out":{"zipline-tower":1}},{"id":"base-zipline","name":"Base Zipline","category":"transport","row":1,"time":0.16666666666666666,"producers":["construction-station"],"in":{"aluminium-plate":8,"aluminium-frame":12},"out":{"base-zipline":1}},{"id":"aircraft-port","name":"Aircraft Port","category":"transport","row":1,"time":0.16666666666666666,"producers":["construction-station"],"in":{"lithium-rod":16,"reinforced-plate":32},"out":{"aircraft-port":1}},{"id":"basic-jet","name":"basic-jet","category":"aircraft","row":1,"time":0.16666666666666666,"producers":["aircraft-port"],"in":{"rocket-power-cell":32,"reinforced-plate":32},"out":{"basic-jet":1}},{"id":"repair-helicopter","name":"repair-helicopter","category":"aircraft","row":1,"time":0.16666666666666666,"producers":["aircraft-port"],"in":{"neodymium-ore":16,"rocket-power-cell":32,"reinforced-plate":24,"high-tech-alloy":32},"out":{"repair-helicopter":1}},{"id":"powered-glider","name":"powered-glider","category":"aircraft","row":1,"time":0.16666666666666666,"producers":["aircraft-port"],"in":{"rocket-power-cell":16,"reinforced-plate":32},"out":{"powered-glider":1}},{"id":"advanced-jet","name":"advanced-jet","category":"aircraft","row":1,"time":0.16666666666666666,"producers":["aircraft-port"],"in":{"xenium-bar":6,"rocket-power-cell":32,"reinforced-plate":64},"out":{"advanced-jet":1}}],"categories":[{"id":"ore","name":"Ore","icon":"iron-ore"},{"id":"materials","name":"Materials","icon":"iron-bar"},{"id":"products","name":"Products","icon":"repair-plate-t1"},{"id":"building","name":"Building","icon":"miner"},{"id":"base-structure","name":"Base Structure","icon":"floor"},{"id":"base-tech","name":"Base Tech","icon":"construction-station"},{"id":"consumables","name":"Consumables","icon":"mini-charge-pack"},{"id":"terraform","name":"Terraform","icon":"terraform-engine-command-center"},{"id":"transport","name":"Transport","icon":"zipline-tower"},{"id":"aircraft","name":"Aircraft","icon":"basic-jet"},{"id":"item","name":"Items","icon":"computer-chip-t1"}],"icons":[{"id":"acid","position":"0px 0px","color":"#6d7682"},{"id":"advanced-jet","position":"-64px 0px","color":"#4f5b62"},{"id":"aircraft-port","position":"-128px 0px","color":"#41363f"},{"id":"aluminium-bar","position":"-192px 0px","color":"#585d61"},{"id":"aluminium-frame","position":"-256px 0px","color":"#62666b"},{"id":"aluminium-plate","position":"-320px 0px","color":"#6c7074"},{"id":"base-zipline","position":"-384px 0px","color":"#2e3a46"},{"id":"basic-jet","position":"-448px 0px","color":"#414c54"},{"id":"bauxite-ore","position":"0px -64px","color":"#5c4d53"},{"id":"cargo-drone","position":"-64px -64px","color":"#3a4d55"},{"id":"charge-gem","position":"-128px -64px","color":"#755f38"},{"id":"charge-pack","position":"-192px -64px","color":"#6b7570"},{"id":"charged-gem","position":"-256px -64px","color":"#755f38"},{"id":"charging-platform","position":"-320px -64px","color":"#415b58"},{"id":"coal","position":"-384px -64px","color":"#373433"},{"id":"cobalt","position":"-448px -64px","color":"#225580"},{"id":"computer-chip-t1","position":"0px -128px","color":"#3e5e30"},{"id":"computer-chip-t2","position":"-64px -128px","color":"#766131"},{"id":"construction-station","position":"-128px -128px","color":"#364047"},{"id":"copper-bar","position":"-192px -128px","color":"#874a3a"},{"id":"copper-ore","position":"-256px -128px","color":"#683e2f"},{"id":"copper-wire","position":"-320px -128px","color":"#6f4339"},{"id":"debri","position":"-384px -128px","color":"#323940"},{"id":"defense-module-t1","position":"-448px -128px","color":"#21672b"},{"id":"defense-module-t2","position":"0px -192px","color":"#23545a"},{"id":"defense-module-t3","position":"-64px -192px","color":"#372b53"},{"id":"defense-module-t4","position":"-128px -192px","color":"#783d32"},{"id":"defense-module-t5","position":"-192px -192px","color":"#5a2d2b"},{"id":"dimond","position":"-256px -192px","color":"#a0a2a3"},{"id":"dna-processor","position":"-320px -192px","color":"#3c4a51"},{"id":"door","position":"-384px -192px","color":"#39434d"},{"id":"drone-control-tower","position":"-448px -192px","color":"#2f3a43"},{"id":"drone-view-constructor","position":"0px -256px","color":"#3d474d"},{"id":"dust-resistant-crystal","position":"-64px -256px","color":"#7e7942"},{"id":"elevator-shaft","position":"-128px -256px","color":"#404a53"},{"id":"elevator","position":"-192px -256px","color":"#4d4d53"},{"id":"factory-(base)","position":"-256px -256px","color":"#455259"},{"id":"factory","position":"-320px -256px","color":"#455157"},{"id":"floor","position":"-384px -256px","color":"#4c5862"},{"id":"foundation-floor","position":"-448px -256px","color":"#37424c"},{"id":"foundation","position":"0px -320px","color":"#333e48"},{"id":"gas-canister","position":"-64px -320px","color":"#375860"},{"id":"gas-dispersion-drone","position":"-128px -320px","color":"#3b4450"},{"id":"gas-drone-launch-platform","position":"-192px -320px","color":"#3b3a3f"},{"id":"geothermal-power-plant","position":"-256px -320px","color":"#475555"},{"id":"glass-floor","position":"-320px -320px","color":"#444c59"},{"id":"glass-wall","position":"-384px -320px","color":"#2b3848"},{"id":"gold-bar","position":"-448px -320px","color":"#957a37"},{"id":"gold-ore","position":"0px -384px","color":"#6b5636"},{"id":"graphite","position":"-64px -384px","color":"#323940"},{"id":"healing-station","position":"-128px -384px","color":"#454e57"},{"id":"health-pack","position":"-192px -384px","color":"#7a766e"},{"id":"heavy-reinforced-plate","position":"-256px -384px","color":"#474f5c"},{"id":"high-powered-mining-laser","position":"-320px -384px","color":"#2e3943"},{"id":"high-tech-alloy","position":"-384px -384px","color":"#1b7f85"},{"id":"iron-bar","position":"-448px -384px","color":"#464a4a"},{"id":"iron-ore","position":"0px -448px","color":"#3b3936"},{"id":"lamp","position":"-64px -448px","color":"#3c4445"},{"id":"large-planter","position":"-128px -448px","color":"#3d454e"},{"id":"large-storage","position":"-192px -448px","color":"#424248"},{"id":"lightning-tower","position":"-256px -448px","color":"#383b33"},{"id":"lithium-rod","position":"-320px -448px","color":"#6c6277"},{"id":"lithium","position":"-384px -448px","color":"#887b93"},{"id":"logistic-storage","position":"-448px -448px","color":"#41494f"},{"id":"logistic-storage-(base)","position":"0px -512px","color":"#3e474e"},{"id":"miner-t1","position":"-64px -512px","color":"#475158"},{"id":"miner-t2","position":"-128px -512px","color":"#475158"},{"id":"miner","position":"-192px -512px","color":"#475158"},{"id":"mini-charge-pack","position":"-256px -512px","color":"#69716e"},{"id":"mini-logistic-storage-(base)","position":"-320px -512px","color":"#38434c"},{"id":"mini-logistic-storage","position":"-384px -512px","color":"#333d46"},{"id":"movement-pack","position":"-448px -512px","color":"#5f6a7c"},{"id":"mysterious-rock","position":"0px -576px","color":"#9b99bc"},{"id":"neodymium-bar","position":"-64px -576px","color":"#254936"},{"id":"neodymium-ore","position":"-128px -576px","color":"#394131"},{"id":"network-chip","position":"-192px -576px","color":"#444f4c"},{"id":"network-receiver","position":"-256px -576px","color":"#3b383c"},{"id":"network-tower","position":"-320px -576px","color":"#414951"},{"id":"nuclear-power-plant","position":"-384px -576px","color":"#4a4d4b"},{"id":"placeholder","position":"-448px -576px","color":"#25313c"},{"id":"planter","position":"0px -640px","color":"#4e5259"},{"id":"player-upgrade-station","position":"-64px -640px","color":"#454c52"},{"id":"powdered-xenium","position":"-128px -640px","color":"#542e38"},{"id":"power-cell","position":"-192px -640px","color":"#546b6e"},{"id":"powered-glider","position":"-256px -640px","color":"#323e47"},{"id":"radar-upgrade-module","position":"-320px -640px","color":"#2e4953"},{"id":"radiant-gem","position":"-384px -640px","color":"#7a363c"},{"id":"radio-active-core","position":"-448px -640px","color":"#257b9d"},{"id":"radioactive-crystal-t1","position":"0px -704px","color":"#964ea0"},{"id":"radioactive-crystal-t2","position":"-64px -704px","color":"#92593d"},{"id":"radioactive-crystal-t3","position":"-128px -704px","color":"#298c4e"},{"id":"rail","position":"-192px -704px","color":"#2a3946"},{"id":"reinforced-plate","position":"-256px -704px","color":"#3e4954"},{"id":"repair-drone","position":"-320px -704px","color":"#3a4143"},{"id":"repair-helicopter","position":"-384px -704px","color":"#424950"},{"id":"repair-plate-t1","position":"-448px -704px","color":"#4a4f52"},{"id":"repair-plate-t2","position":"0px -768px","color":"#395143"},{"id":"repair-plate-t3","position":"-64px -768px","color":"#663e40"},{"id":"resource-detector","position":"-128px -768px","color":"#2b4147"},{"id":"rocket-launch-platform","position":"-192px -768px","color":"#333f4a"},{"id":"rocket-power-cell","position":"-256px -768px","color":"#6d7071"},{"id":"rocket-t1","position":"-320px -768px","color":"#434948"},{"id":"rocket-t2","position":"-384px -768px","color":"#41424f"},{"id":"rocket-t3","position":"-448px -768px","color":"#493f45"},{"id":"salt","position":"0px -832px","color":"#8b8c8e"},{"id":"server-power-generator-t1","position":"-64px -832px","color":"#445150"},{"id":"server-power-generator-t2","position":"-128px -832px","color":"#4d4f45"},{"id":"server-t1","position":"-192px -832px","color":"#3c454c"},{"id":"server-t2","position":"-256px -832px","color":"#383539"},{"id":"shield-station","position":"-320px -832px","color":"#394655"},{"id":"silica","position":"-384px -832px","color":"#627888"},{"id":"silicon","position":"-448px -832px","color":"#627888"},{"id":"skybase-server-monitor","position":"0px -896px","color":"#2e3840"},{"id":"slope-down","position":"-64px -896px","color":"#414a54"},{"id":"slope-up","position":"-128px -896px","color":"#3c454f"},{"id":"sloped-rail","position":"-192px -896px","color":"#333e4a"},{"id":"small-planter","position":"-256px -896px","color":"#4e5259"},{"id":"small-storage","position":"-320px -896px","color":"#404851"},{"id":"soil","position":"-384px -896px","color":"#2f3339"},{"id":"steel-bar","position":"-448px -896px","color":"#74787b"},{"id":"steel-beam","position":"0px -960px","color":"#595f66"},{"id":"storm-defense-system","position":"-64px -960px","color":"#2f3c45"},{"id":"storm-probe-monitor","position":"-128px -960px","color":"#324346"},{"id":"storm-probe","position":"-192px -960px","color":"#2c3a48"},{"id":"storm-warning-display","position":"-256px -960px","color":"#2a313b"},{"id":"structural-composite","position":"-320px -960px","color":"#354553"},{"id":"sulphur","position":"-384px -960px","color":"#757831"},{"id":"supercharged-gem","position":"-448px -960px","color":"#62878f"},{"id":"temperature-display","position":"0px -1024px","color":"#2e353c"},{"id":"terraform-engine-command-center","position":"-64px -1024px","color":"#2f414b"},{"id":"titanium-bar","position":"-128px -1024px","color":"#374755"},{"id":"titanium-ore","position":"-192px -1024px","color":"#474b51"},{"id":"tower-down","position":"-256px -1024px","color":"#413a3c"},{"id":"tower-up","position":"-320px -1024px","color":"#3f3b3f"},{"id":"wall","position":"-384px -1024px","color":"#313d49"},{"id":"weather-station","position":"-448px -1024px","color":"#30414b"},{"id":"xenium-bar","position":"0px -1088px","color":"#4f2c37"},{"id":"xenium-ore","position":"-64px -1088px","color":"#533c3d"},{"id":"xenosulfate","position":"-128px -1088px","color":"#686264"},{"id":"zipline-tower","position":"-192px -1088px","color":"#253441"}],"flags":[]}